testcontainers/minio/__init__.py
tests/test_minio.py
testcontainers_minio-0.0.1rc1.dist-info/METADATA
testcontainers_minio-0.0.1rc1.dist-info/WHEEL
testcontainers_minio-0.0.1rc1.dist-info/top_level.txt
testcontainers_minio-0.0.1rc1.dist-info/RECORD
